bsp2obj/__init__.py
bsp2obj/bsp.py
bsp2obj/command_line.py
bsp2obj/helpers.py
bsp2obj/pak.py
bsp2obj-0.2.dist-info/DESCRIPTION.rst
bsp2obj-0.2.dist-info/METADATA
bsp2obj-0.2.dist-info/RECORD
bsp2obj-0.2.dist-info/WHEEL
bsp2obj-0.2.dist-info/entry_points.txt
bsp2obj-0.2.dist-info/metadata.json
bsp2obj-0.2.dist-info/top_level.txt
