Metadata-Version: 2.0
Name: bsp2obj
Version: 0.2
Summary: A utility for converting BSP maps to the OBJ/MTL file format
Home-page: https://github.com/measuredweighed/BSP2OBJ
Author: @measuredweighed
Author-email: UNKNOWN
License: MIT
Platform: UNKNOWN
Requires-Dist: pillow
Requires-Dist: enum
